crow_security/__init__.py
crow_security/crow.py
crow_security/urls.py
crow_security-0.2.2.dist-info/LICENSE.txt
crow_security-0.2.2.dist-info/METADATA
crow_security-0.2.2.dist-info/WHEEL
crow_security-0.2.2.dist-info/top_level.txt
crow_security-0.2.2.dist-info/RECORD
